setup.py
target_api_client/__init__.py
target_api_client/config.py
target_api_client/core.py
target_api_client/errors.py
target_api_client.egg-info/PKG-INFO
target_api_client.egg-info/SOURCES.txt
target_api_client.egg-info/dependency_links.txt
target_api_client.egg-info/not-zip-safe
target_api_client.egg-info/requires.txt
target_api_client.egg-info/top_level.txt