Metadata-Version: 1.1
Name: target-api-client
Version: 1.0
Summary: Target.com API Client
Home-page: https://github.com/kronas/python-target-api-client
Author: Kronas
Author-email: kronas.sw@gmail.com
License: MIT
Platform: UNKNOWN
Classifier: Development Status :: 5 - Production/Stable
Classifier: Intended Audience :: Developers
Classifier: License :: OSI Approved :: MIT License
Classifier: Natural Language :: English
Classifier: Operating System :: OS Independent
Classifier: Programming Language :: Python :: 2
Classifier: Topic :: Software Development :: Libraries :: Python Modules
